lexer_tools/__init__.py
lexer_tools/core.py
lexer_tools/data/exp1/Untitled.ipynb
lexer_tools/data/exp1/exp1.ipynb
lexer_tools/data/exp1/removalrepeat.py
lexer_tools/data/exp1/replacerRE.py
lexer_tools/data/exp1/replacerantonym.py
lexer_tools/data/exp1/replacesyn.py
lexer_tools/data/exp1/syn.csv
lexer_tools/data/exp1/syn.yaml
lexer_tools/data/exp2/SAMPLETEXT.txt
lexer_tools/data/exp2/exp2.ipynb
lexer_tools/data/exp3/Text.txt
lexer_tools/data/exp3/exp3.ipynb
lexer_tools/data/exp4/AttachmentAmbiguity.txt
lexer_tools/data/exp4/exp4.ipynb
lexer_tools/data/exp5/exp5.ipynb
lexer_tools-2.1.1.dist-info/METADATA
lexer_tools-2.1.1.dist-info/WHEEL
lexer_tools-2.1.1.dist-info/top_level.txt
lexer_tools-2.1.1.dist-info/RECORD
