Metadata-Version: 2.1
Name: lexer-tools
Version: 2.1.1
Summary: A lexer-tools is a python package that help student on NLP
Author: Sam Anderson
Author-email: samanderson69@gmail.com
Classifier: Programming Language :: Python :: 3
Classifier: License :: OSI Approved :: MIT License
Classifier: Operating System :: OS Independent
Requires-Python: >=3.6
